{
  "node": {
    "15670382649263166d0619a173cbbd61410d2d34": {
      "workers": {
        "app/page": "(action-browser)/./node_modules/next/dist/build/webpack/loaders/next-flight-action-entry-loader.js?actions=%5B%5B%22%2FUsers%2FMAC%2FDownloads%2FMetaschool%2FFlashCard%2Fnode_modules%2F%40clerk%2Fnextjs%2Fdist%2Fesm%2Fapp-router%2Fserver-actions.js%22%2C%5B%22invalidateCacheAction%22%5D%5D%5D&__client_imported__=true!",
        "app/dashboard/page": "(action-browser)/./node_modules/next/dist/build/webpack/loaders/next-flight-action-entry-loader.js?actions=%5B%5B%22%2FUsers%2FMAC%2FDownloads%2FMetaschool%2FFlashCard%2Fnode_modules%2F%40clerk%2Fnextjs%2Fdist%2Fesm%2Fapp-router%2Fserver-actions.js%22%2C%5B%22invalidateCacheAction%22%5D%5D%5D&__client_imported__=true!"
      },
      "layer": {
        "app/page": "action-browser",
        "app/dashboard/page": "action-browser"
      }
    }
  },
  "edge": {},
  "encryptionKey": "sNsqy0vrC+3Hf54PhXUsfgGTG5O6ne4DQV2l+fA4aZQ="
}